{
	"format_version": "1.8.0",
	"animations": {
		"animation.model.walking": {
			"loop": true,
			"animation_length": 0.8,
			"bones": {
				"leg2": {
					"rotation": {
						"0.0": {
							"vector": [0, 0, 0]
						},
						"0.32": {
							"vector": [12.5, 0, 0]
						},
						"0.64": {
							"vector": [-12.5, 0, 0]
						},
						"0.8": {
							"vector": [0, 0, 0]
						}
					},
					"position": {
						"0.0": {
							"vector": [0, 0, 0]
						},
						"0.32": {
							"vector": [0, 1, 3]
						},
						"0.64": {
							"vector": [0, -1, -3]
						},
						"0.8": {
							"vector": [0, 0, 0]
						}
					}
				},
				"leg3": {
					"rotation": {
						"0.0": {
							"vector": [0, 0, 0]
						},
						"0.32": {
							"vector": [12.5, 0, 0]
						},
						"0.64": {
							"vector": [-12.5, 0, 0]
						},
						"0.8": {
							"vector": [0, 0, 0]
						}
					},
					"position": {
						"0.0": {
							"vector": [0, 0, 2]
						},
						"0.32": {
							"vector": [0, -2, 2]
						},
						"0.64": {
							"vector": [0, 2, -2]
						},
						"0.8": {
							"vector": [0, 0, 2]
						}
					}
				},
				"leg4": {
					"rotation": {
						"0.0": {
							"vector": [0, 0, 0]
						},
						"0.32": {
							"vector": [-12.5, 0, 0]
						},
						"0.64": {
							"vector": [12.5, 0, 0]
						},
						"0.8": {
							"vector": [0, 0, 0]
						}
					},
					"position": {
						"0.0": {
							"vector": [0, 0, 0]
						},
						"0.32": {
							"vector": [0, 2, -2]
						},
						"0.64": {
							"vector": [0, -2, 2]
						},
						"0.8": {
							"vector": [0, 0, 0]
						}
					}
				}
			}
		},
		"animation.model.idle": {
			"loop": true
		}
	},
	"geckolib_format_version": 2
}